yv_xtract/__init__.py
yv_xtract/terminal_utils.py
yv_xtract/video_downloader.py
yv_xtract/yte.py
yv_xtract/yvx_config.py
yv_xtract-1.2.dist-info/LICENSE
yv_xtract-1.2.dist-info/METADATA
yv_xtract-1.2.dist-info/WHEEL
yv_xtract-1.2.dist-info/entry_points.txt
yv_xtract-1.2.dist-info/top_level.txt
yv_xtract-1.2.dist-info/RECORD
