Metadata-Version: 2.1
Name: yv-xtract
Version: 1.2
Summary: CLI tool to download YouTube videos
Author-email: Ricardo Ramirez <ricaiditodev@gmail.com>
License: MIT License
Project-URL: Repository, https://github.com/Ricaidito/yv-xtract.git
Project-URL: Bug Tracker, https://github.com/Ricaidito/yv-xtract/issues
Keywords: python,youtube,video,downloader,cli,mp3,mp4,gif
Classifier: Programming Language :: Python :: 3
Classifier: Operating System :: OS Independent
Requires-Python: >=3.7
License-File: LICENSE
Requires-Dist: pytube
Requires-Dist: moviepy
Requires-Dist: termcolor
